blueskysight/conf_sample.py
blueskysight/config.py
blueskysight/firehose.py
blueskysight/jetstream.py
blueskysight/stream.py
blueskysight/utils.py
blueskysight-1.0.0.dist-info/COPYING
blueskysight-1.0.0.dist-info/METADATA
blueskysight-1.0.0.dist-info/WHEEL
blueskysight-1.0.0.dist-info/entry_points.txt
blueskysight-1.0.0.dist-info/RECORD
