Metadata-Version: 2.3
Name: BlueSkySight
Version: 1.0.0
Summary: A client to gather vulnerability-related information from Bluesky.
License: GPL-3.0-or-later
Keywords: Vulnerability-Lookup,Vulnerability,CVE,Bluesky
Author: Cédric Bonhomme
Author-email: cedric.bonhomme@circl.lu
Requires-Python: >=3.10,<4.0
Classifier: Development Status :: 5 - Production/Stable
Classifier: Environment :: Console
Classifier: Intended Audience :: Developers
Classifier: Intended Audience :: Science/Research
Classifier: License :: OSI Approved :: GNU General Public License v3 or later (GPLv3+)
Classifier: Operating System :: POSIX :: Linux
Classifier: Programming Language :: Python :: 3
Classifier: Programming Language :: Python :: 3.10
Classifier: Programming Language :: Python :: 3.11
Classifier: Programming Language :: Python :: 3.12
Classifier: Programming Language :: Python :: 3.13
Classifier: Topic :: Security
Requires-Dist: cbor2 (>=5.6.5)
Requires-Dist: httpx (>=0.28.1)
Requires-Dist: pyvulnerabilitylookup (>=2.2.0)
Requires-Dist: valkey (>=6.1.0,<7.0.0)
Requires-Dist: websockets (>=14.1)
Requires-Dist: zstandard (>=0.23.0)
Project-URL: Changelog, https://github.com/vulnerability-lookup/BlueSkySight/blob/main/CHANGELOG.md
Project-URL: Homepage, https://github.com/vulnerability-lookup/BlueSkySight
Project-URL: Repository, https://github.com/vulnerability-lookup/BlueSkySight
